{
  "kind": "build_request",
  "title": "Switch universe source to Binance USDT-M Futures",
  "projectName": "G100 RSI 3TF Paper Engine",
  "priority": "high",
  "requirements": [
    {
      "id": "REQ-34",
      "text": "Replace universe endpoint in safeFetch base configuration from https://api.binance.com to https://fapi.binance.com for Futures API access",
      "target": "frontend",
      "source": {
        "messageIds": [
          "msg-recent"
        ],
        "quotes": [
          "Switch universe source to Binance USDT-M Futures only",
          "Replace universe endpoint with: https://fapi.binance.com/fapi/v1/ticker/24hr"
        ]
      },
      "acceptanceCriteria": [
        "safeFetch utility uses https://fapi.binance.com as base URL",
        "All universe-related fetches target Futures API endpoints"
      ]
    },
    {
      "id": "REQ-35",
      "text": "Update fetchUniverse24h function in binanceApi.ts to call https://fapi.binance.com/fapi/v1/ticker/24hr endpoint for Futures USDT-M perpetual contracts",
      "target": "frontend",
      "source": {
        "messageIds": [
          "msg-recent"
        ],
        "quotes": [
          "Replace universe endpoint with: https://fapi.binance.com/fapi/v1/ticker/24hr"
        ]
      },
      "acceptanceCriteria": [
        "fetchUniverse24h calls /fapi/v1/ticker/24hr endpoint",
        "Function returns array of Futures ticker data or empty array on failure"
      ]
    },
    {
      "id": "REQ-36",
      "text": "Modify universeFilter.ts to filter universe to ONLY symbols ending with 'USDT' and explicitly exclude all symbols containing 'USDC' (case-insensitive check on the full symbol string)",
      "target": "frontend",
      "source": {
        "messageIds": [
          "msg-recent"
        ],
        "quotes": [
          "Universe must include ONLY: Symbols ending with USDT",
          "Explicitly EXCLUDE: All symbols containing USDC"
        ]
      },
      "acceptanceCriteria": [
        "Filter rejects any symbol not ending with 'USDT'",
        "Filter rejects any symbol containing 'USDC' anywhere in the string (case-insensitive)",
        "USDC exclusion check runs before volume threshold filtering"
      ]
    },
    {
      "id": "REQ-37",
      "text": "Add validation in universeFilter.ts to exclude stable-to-stable pairs by checking if base asset (symbol without 'USDT' suffix) matches any stablecoin identifier: USDC, BUSD, TUSD, FDUSD, USDP, DAI, UST, PAX, USD1 (case-insensitive)",
      "target": "frontend",
      "source": {
        "messageIds": [
          "msg-recent"
        ],
        "quotes": [
          "Explicitly EXCLUDE: All stable/stable pairs"
        ]
      },
      "acceptanceCriteria": [
        "Extract base asset by removing 'USDT' suffix",
        "Reject symbol if base asset matches any stablecoin identifier (case-insensitive)",
        "Stable-to-stable exclusion runs after USDT/USDC filtering but before volume threshold"
      ]
    },
    {
      "id": "REQ-38",
      "text": "Update universeFilter.ts to parse quoteVolume using Number(item.quoteVolume) and apply volume threshold filter (>= 5,000,000) AFTER proper numeric conversion",
      "target": "frontend",
      "source": {
        "messageIds": [
          "msg-recent"
        ],
        "quotes": [
          "Parse quoteVolume using: const vol = Number(item.quoteVolume)",
          "Apply volume threshold AFTER proper parsing"
        ]
      },
      "acceptanceCriteria": [
        "Parse quoteVolume with Number() before comparison",
        "Volume threshold check (>= 5,000,000) happens after numeric conversion",
        "NaN values from parsing are logged but not excluded from processing"
      ]
    },
    {
      "id": "REQ-39",
      "text": "Add UNIVERSE_SOURCE log event immediately when fetchUniverse24h is called, with payload containing { source: 'FUTURES_USDTM', endpoint: '/fapi/v1/ticker/24hr' }",
      "target": "frontend",
      "source": {
        "messageIds": [
          "msg-recent"
        ],
        "quotes": [
          "Log: UNIVERSE_SOURCE = FUTURES_USDTM"
        ]
      },
      "acceptanceCriteria": [
        "UNIVERSE_SOURCE event logged at start of universe fetch",
        "Payload includes source='FUTURES_USDTM' and endpoint path",
        "Event appears in logs before UNIVERSE_FILTERED or UNIVERSE_DEBUG_SAMPLE"
      ]
    },
    {
      "id": "REQ-40",
      "text": "Update universeFilter.ts fallback logic to apply same USDT-only, no-USDC, no-stable/stable filters when filtered.length === 0, then sort by quoteVolume descending and return exactly top 5 symbols (not 20)",
      "target": "frontend",
      "source": {
        "messageIds": [
          "msg-recent"
        ],
        "quotes": [
          "Fallback must also respect: USDT only, No USDC, No stable/stable, Max 5 symbols"
        ]
      },
      "acceptanceCriteria": [
        "Fallback filters raw universe to USDT-ending symbols only",
        "Fallback excludes all USDC-containing symbols",
        "Fallback excludes stable-to-stable pairs (base asset check)",
        "Fallback sorts remaining by quoteVolume DESC and returns exactly 5 symbols",
        "UNIVERSE_FALLBACK event logged when fallback executes"
      ]
    },
    {
      "id": "REQ-41",
      "text": "Add UNIVERSE_SOURCE to LogEntry type union in frontend/src/types/store.ts",
      "target": "frontend",
      "source": {
        "messageIds": [
          "msg-recent"
        ],
        "quotes": [
          "Log: UNIVERSE_SOURCE = FUTURES_USDTM"
        ]
      },
      "acceptanceCriteria": [
        "UNIVERSE_SOURCE added to LogEntry type union",
        "Type definition follows existing log structure with timestamp and payload fields"
      ]
    },
    {
      "id": "REQ-42",
      "text": "Update LogsTab.tsx to display UNIVERSE_SOURCE log event type with default color coding (not red or yellow)",
      "target": "frontend",
      "source": {
        "messageIds": [
          "msg-recent"
        ],
        "quotes": [
          "Log: UNIVERSE_SOURCE = FUTURES_USDTM"
        ]
      },
      "acceptanceCriteria": [
        "UNIVERSE_SOURCE events render in logs panel",
        "Event uses default color (not error red or warning yellow)",
        "Payload displays source and endpoint information"
      ]
    }
  ],
  "constraints": [
    "Do NOT modify RSI calculation logic (rsiCalculator.ts)",
    "Do NOT modify entry gate rules (entryGates.ts)",
    "Do NOT modify exit evaluation logic (exitEvaluator.ts)",
    "Do NOT modify risk model calculations (riskManager.ts)",
    "Do NOT modify strategy constants (1% risk, 0.6% stop, TP1/TP2 levels, 45min time stop)",
    "Do NOT change engine tick interval (15 seconds)",
    "Do NOT change TOP5 rotation schedule (15 minutes)",
    "Do NOT change cooldown duration (30 minutes after SL only)",
    "Preserve all existing logging events and log structure"
  ],
  "nonGoals": [
    "Modifying RSI parameters or calculation method",
    "Changing entry/exit gate thresholds or conditions",
    "Adjusting position sizing or risk percentages",
    "Adding new timeframes beyond 1m/5m/15m",
    "Implementing SHORT positions",
    "Adding WebSocket or real-time data streams",
    "Fetching Spot market data",
    "Mixing Spot and Futures data in universe"
  ],
  "imageRequirements": {
    "required": [],
    "edits": []
  }
}